JavaSwingJiaocheng30FenzhongWanzhuanSwingJiemianshejiCYuyanZhongwenwang/README.md
JavaSwingJiaocheng30FenzhongWanzhuanSwingJiemianshejiCYuyanZhongwenwang/__init__.py
JavaSwingJiaocheng30FenzhongWanzhuanSwingJiemianshejiCYuyanZhongwenwang/__main__.py
JavaSwingJiaocheng30FenzhongWanzhuanSwingJiemianshejiCYuyanZhongwenwang/file.epub
JavaSwingJiaocheng30FenzhongWanzhuanSwingJiemianshejiCYuyanZhongwenwang/index.html
JavaSwingJiaocheng30FenzhongWanzhuanSwingJiemianshejiCYuyanZhongwenwang/css/__init__.py
JavaSwingJiaocheng30FenzhongWanzhuanSwingJiemianshejiCYuyanZhongwenwang/css/annotations.css
JavaSwingJiaocheng30FenzhongWanzhuanSwingJiemianshejiCYuyanZhongwenwang/css/main.css
JavaSwingJiaocheng30FenzhongWanzhuanSwingJiemianshejiCYuyanZhongwenwang/css/normalize.css
JavaSwingJiaocheng30FenzhongWanzhuanSwingJiemianshejiCYuyanZhongwenwang/css/popup.css
JavaSwingJiaocheng30FenzhongWanzhuanSwingJiemianshejiCYuyanZhongwenwang/font/__init__.py
JavaSwingJiaocheng30FenzhongWanzhuanSwingJiemianshejiCYuyanZhongwenwang/font/fontello.eot
JavaSwingJiaocheng30FenzhongWanzhuanSwingJiemianshejiCYuyanZhongwenwang/font/fontello.svg
JavaSwingJiaocheng30FenzhongWanzhuanSwingJiemianshejiCYuyanZhongwenwang/font/fontello.ttf
JavaSwingJiaocheng30FenzhongWanzhuanSwingJiemianshejiCYuyanZhongwenwang/font/fontello.woff
JavaSwingJiaocheng30FenzhongWanzhuanSwingJiemianshejiCYuyanZhongwenwang/img/__init__.py
JavaSwingJiaocheng30FenzhongWanzhuanSwingJiemianshejiCYuyanZhongwenwang/img/annotator-glyph-sprite.png
JavaSwingJiaocheng30FenzhongWanzhuanSwingJiemianshejiCYuyanZhongwenwang/img/annotator-icon-sprite.png
JavaSwingJiaocheng30FenzhongWanzhuanSwingJiemianshejiCYuyanZhongwenwang/img/apple-touch-icon.png
JavaSwingJiaocheng30FenzhongWanzhuanSwingJiemianshejiCYuyanZhongwenwang/img/cancelfullscreen.png
JavaSwingJiaocheng30FenzhongWanzhuanSwingJiemianshejiCYuyanZhongwenwang/img/close.png
JavaSwingJiaocheng30FenzhongWanzhuanSwingJiemianshejiCYuyanZhongwenwang/img/fullscreen.png
java_swing_jiaocheng_30_fenzhong_wanzhuan_swing_jiemiansheji_c_yuyan_zhongwenwang-2024.3.4.0.dist-info/METADATA
java_swing_jiaocheng_30_fenzhong_wanzhuan_swing_jiemiansheji_c_yuyan_zhongwenwang-2024.3.4.0.dist-info/WHEEL
java_swing_jiaocheng_30_fenzhong_wanzhuan_swing_jiemiansheji_c_yuyan_zhongwenwang-2024.3.4.0.dist-info/entry_points.txt
java_swing_jiaocheng_30_fenzhong_wanzhuan_swing_jiemiansheji_c_yuyan_zhongwenwang-2024.3.4.0.dist-info/top_level.txt
java_swing_jiaocheng_30_fenzhong_wanzhuan_swing_jiemiansheji_c_yuyan_zhongwenwang-2024.3.4.0.dist-info/RECORD
